<Properties StartupConfiguration="{9B5496B4-A6F3-4DBC-A99E-F0C9391257E1}|https">
  <MonoDevelop.Ide.ItemProperties.API PreferredExecutionTarget="/Applications/Firefox.app" />
  <MonoDevelop.Ide.Workbench ActiveDocument="Centurion/Program.cs">
    <Files>
      <File FileName="Centurion/Program.cs" Line="31" Column="1" />
      <File FileName="Helpers/CamelCase.cs" Line="1" Column="1" />
    </Files>
    <Pads>
      <Pad Id="ProjectPad">
        <State name="__root__">
          <Node name="Centurion" expanded="True">
            <Node name="Busisnnes" expanded="True">
              <Node name="Helpers" expanded="True" />
            </Node>
            <Node name="API" expanded="True">
              <Node name="Program.cs" selected="True" />
            </Node>
          </Node>
        </State>
      </Pad>
    </Pads>
  </MonoDevelop.Ide.Workbench>
  <MultiItemStartupConfigurations />
  <MonoDevelop.Ide.DebuggingService.Breakpoints />
  <MonoDevelop.Ide.DebuggingService.PinnedWatches />
  <MonoDevelop.Ide.Workspace ActiveConfiguration="Debug" />
  <MonoDevelop.Ide.ItemProperties.Busisnnes.Session FirstBuild="True" />
</Properties>